ElliShape/ElliShape.py
ElliShape/__init__.py
ElliShape/functions/EFA.py
ElliShape/functions/__init__.py
ElliShape/functions/binarize_func.py
ElliShape/functions/cal_area_c.py
ElliShape/functions/calc_dc_components_modify.py
ElliShape/functions/calc_traversal_dist.py
ElliShape/functions/calc_traversal_dist_modify.py
ElliShape/functions/calc_traversal_time.py
ElliShape/functions/calc_traversal_time_modify.py
ElliShape/functions/chain_code_func.py
ElliShape/functions/code2axis.py
ElliShape/functions/contour_extraction_func.py
ElliShape/functions/corrosion_func.py
ElliShape/functions/dilation_func.py
ElliShape/functions/enhancement_func.py
ElliShape/functions/fast_calc_harmonic_coefficients_modify.py
ElliShape/functions/fourier_approx_norm_modify.py
ElliShape/functions/get_curve_from_efd.py
ElliShape/functions/grayscale_func.py
ElliShape/functions/gui_chain_code_func.py
ElliShape/functions/inverted_colors_func.py
ElliShape/functions/is_completed_chain_code.py
ElliShape/functions/plot_chain_code.py
ElliShape/functions/plot_fourier_approx_modify.py
ElliShape/functions/write_Data_To_File.py
ElliShape/label/calc_dc_components_modify.py
ElliShape/label/calc_harmonic_coefficients_modify.py
ElliShape/label/calc_traversal_dist.py
ElliShape/label/calc_traversal_time.py
ElliShape/label/fourier_approx_norm_modify.py
ElliShape/segment_anything/__init__.py
ElliShape/segment_anything/automatic_mask_generator.py
ElliShape/segment_anything/build_sam.py
ElliShape/segment_anything/predictor.py
ElliShape/segment_anything/modeling/__init__.py
ElliShape/segment_anything/modeling/common.py
ElliShape/segment_anything/modeling/image_encoder.py
ElliShape/segment_anything/modeling/mask_decoder.py
ElliShape/segment_anything/modeling/prompt_encoder.py
ElliShape/segment_anything/modeling/sam.py
ElliShape/segment_anything/modeling/transformer.py
ElliShape/segment_anything/utils/__init__.py
ElliShape/segment_anything/utils/amg.py
ElliShape/segment_anything/utils/onnx.py
ElliShape-1.5.0.dist-info/METADATA
ElliShape-1.5.0.dist-info/WHEEL
ElliShape-1.5.0.dist-info/entry_points.txt
ElliShape-1.5.0.dist-info/top_level.txt
ElliShape-1.5.0.dist-info/RECORD
