Metadata-Version: 2.1
Name: ElliShape
Version: 1.5.0
Summary: Morphological analysis tool
Author-email: Sally yang <2500876951@qq.com>
License: MIT
Project-URL: Homepage, https://www.plantplus.cn/ElliShape/
Classifier: Programming Language :: Python :: 3
Classifier: License :: OSI Approved :: MIT License
Classifier: Operating System :: OS Independent
Requires-Python: >=3.8
Requires-Dist: opencv-python >=4.9.0.80
Requires-Dist: matplotlib >=3.7.2
Requires-Dist: pyqt5 >=5.15.10
Requires-Dist: segment-anything >=1.0
Requires-Dist: torch >=2.2.2
Requires-Dist: torchvision >=0.17.2
Requires-Dist: scipy >=1.10.1
Requires-Dist: openpyxl >=3.1.2
Requires-Dist: numpy >=1.24.3
Requires-Dist: pandas >=2.0.3
Requires-Dist: pillow >=10.2.0
Requires-Dist: PyQt5-sip >=12.13.0
Requires-Dist: PySocks >=1.7.1
Requires-Dist: urllib3 >=2.1.0
Requires-Dist: requests >=2.31.0
Requires-Dist: tqdm >=4.66.5
